Workbook

Sheet Assumptions
B3: FY0 | C3: FY1 | D3: FY2 | E3: FY3 | F3: FY4 | G3: FY5
A5: Operating Assumptions
A6: Revenue Growth (%) | C6: 0.05 | D6: 0.05 | E6: 0.05 | F6: 0.05 | G6: 0.05
A7: Gross Margin (%) | C7: 0.44 | D7: 0.44 | E7: 0.44 | F7: 0.44 | G7: 0.44
A8: Operating Margin (%) | C8: 0.3 | D8: 0.3 | E8: 0.3 | F8: 0.3 | G8: 0.3
A9: Tax Rate (%) | C9: 0.16 | D9: 0.16 | E9: 0.16 | F9: 0.16 | G9: 0.16
A10: Capex (% of Revenue) | C10: 0.03 | D10: 0.03 | E10: 0.03 | F10: 0.03 | G10: 0.03
A11: Depreciation (% of Revenue) | C11: 0.035 | D11: 0.035 | E11: 0.035 | F11: 0.035 | G11: 0.035
A12: Working Capital (% of Revenue) | C12: 0.01 | D12: 0.01 | E12: 0.01 | F12: 0.01 | G12: 0.01
A14: Valuation Assumptions
A15: WACC | C15: 0.08 | D15: 0.08 | E15: 0.08 | F15: 0.08 | G15: 0.08
A16: Terminal Growth | C16: 0.025 | D16: 0.025 | E16: 0.025 | F16: 0.025 | G16: 0.025

Sheet Income statement
B3: FY0 | C3: FY1 | D3: FY2 | E3: FY3 | F3: FY4 | G3: FY5
A5: Revenue | B5: 416161000 | C5: =B5 * (1 + Assumptions!C6) -> 436969050 | D5: =C5 * (1 + Assumptions!D6) -> 4.588175e+08 | E5: =D5 * (1 + Assumptions!E6) -> 4.8175838e+08 | F5: =E5 * (1 + Assumptions!F6) -> 5.058463e+08 | G5: =F5 * (1 + Assumptions!G6) -> 5.3113861e+08
A6: COGS | B6: 220960000 | C6: =C5-C7 -> 244702668 | D6: =D5-D7 -> 2.569378e+08 | E6: =E5-E7 -> 2.6978469e+08 | F6: =F5-F7 -> 2.8327393e+08 | G6: =G5-G7 -> 2.9743762e+08
A7: Gross Profit | B7: 195201000 | C7: =C5*Assumptions!C7 -> 192266382 | D7: =D5*Assumptions!D7 -> 2.018797e+08 | E7: =E5*Assumptions!E7 -> 2.1197369e+08 | F7: =F5*Assumptions!F7 -> 2.2257237e+08 | G7: =G5*Assumptions!G7 -> 2.3370099e+08
A8: Operating Expenses | B8: 62151000 | C8: =C7-C9 -> 61175667 | D8: =D7-D9 -> 64234450 | E8: =E7-E9 -> 67446173 | F8: =F7-F9 -> 70818482 | G8: =G7-G9 -> 74359406
A9: EBIT | B9: 133050000 | C9: =C5 * Assumptions!C8 -> 131090715 | D9: =D5 * Assumptions!D8 -> 1.3764525e+08 | E9: =E5 * Assumptions!E8 -> 1.4452751e+08 | F9: =F5 * Assumptions!F8 -> 1.5175389e+08 | G9: =G5 * Assumptions!G8 -> 1.5934158e+08
A10: Taxes | B10: 20719000 | C10: =C9 * Assumptions!C9 -> 20974514 | D10: =D9 * Assumptions!D9 -> 22023240 | E10: =E9 * Assumptions!E9 -> 23124402 | F10: =F9 * Assumptions!F9 -> 24280622 | G10: =G9 * Assumptions!G9 -> 25494653
A11: Net Income | B11: 93736000 | C11: =C9-C10 -> 1.101162e+08 | D11: =D9-D10 -> 1.1562201e+08 | E11: =E9-E10 -> 1.2140311e+08 | F11: =F9-F10 -> 1.2747327e+08 | G11: =G9-G10 -> 1.3384693e+08

Sheet Balance sheet 
B4: FY0 | C4: FY1 | D4: FY2 | E4: FY3 | F4: FY4 | G4: FY5
A5: Assets
A6: Cash | B6: 54697000 | C6: =B6+'Cash flow'!C16 -> 1.3922336e+08 | D6: =C6+'Cash flow'!D16 -> 2.5692097e+08 | E6: =D6+'Cash flow'!E16 -> 3.8050346e+08 | F6: =E6+'Cash flow'!F16 -> 5.1026508e+08 | G6: =F6+'Cash flow'!G16 -> 6.4651478e+08
A7: PP&E | B7: 49834000 | C7: =B7+'Supporting schedule'!C7 -'Supporting schedule'!C5 -> 47649155 | D7: =C7+'Supporting schedule'!D7 -'Supporting schedule'!D5 -> 45355067 | E7: =D7+'Supporting schedule'!E7 -'Supporting schedule'!E5 -> 42946275 | F7: =E7+'Supporting schedule'!F7 -'Supporting schedule'!F5 -> 40417044 | G7: =F7+'Supporting schedule'!G7 -'Supporting schedule'!G5 -> 37761351
A9: Total Assets | C9: =C6+C7 -> 1.8687251e+08 | D9: =D6+D7 -> 3.0227604e+08 | E9: =E6+E7 -> 4.2344974e+08 | F9: =F6+F7 -> 5.5068213e+08 | G9: =G6+G7 -> 6.8427613e+08
A11: Liabilities & Equity
A12: Debt | B12: 98657000 | C12: =B12 -> 98657000 | D12: =C12 -> 98657000 | E12: =D12 -> 98657000 | F12: =E12 -> 98657000 | G12: =F12 -> 98657000
A13: Equity | B13: 73733000 | C13: =C9-(C12+C14) -> 88215510 | D13: =D9-(D12+D14) -> 2.0361904e+08 | E13: =E9-(E12+E14) -> 3.2479274e+08 | F13: =F9-(F12+F14) -> 4.5202513e+08 | G13: =G9-(G12+G14) -> 5.8561913e+08
A15: Total Liabilites & Equity | C15: =C12+C13+C14 -> 1.8687251e+08 | D15: =D12+D13+D14 -> 3.0227604e+08 | E15: =E12+E13+E14 -> 4.2344974e+08 | F15: =F12+F13+F14 -> 5.5068213e+08 | G15: =G12+G13+G14 -> 6.8427613e+08

Sheet Cash flow
B4: FY0 | C4: FY1 | D4: FY2 | E4: FY3 | F4: FY4 | G4: FY5
A5: Cash Flow From operations
A6: Net Income | C6: ='Income statement'!C11 -> 1.101162e+08 | D6: ='Income statement'!D11 -> 1.1562201e+08 | E6: ='Income statement'!E11 -> 1.2140311e+08 | F6: ='Income statement'!F11 -> 1.2747327e+08 | G6: ='Income statement'!G11 -> 1.3384693e+08
A7: Depreciation | C7: ='Supporting schedule'!C5 -> 15293917 | D7: ='Supporting schedule'!D5 -> 16058613 | E7: ='Supporting schedule'!E5 -> 16861543 | F7: ='Supporting schedule'!F5 -> 17704620 | G7: ='Supporting schedule'!G5 -> 18589851
A8: Change in Working Capital | C8: =-'Supporting schedule'!C10 -> -27774690 | D8: =-'Supporting schedule'!D10 -> -218484.53 | E8: =-'Supporting schedule'!E10 -> -229408.75 | F8: =-'Supporting schedule'!F10 -> -240879.19 | G8: =-'Supporting schedule'!G10 -> -252923.15
A10: Cash Flow From Investing
A11: Capital Expenditure | C11: =-'Supporting schedule'!C7 -> -13109072 | D11: =-'Supporting schedule'!D7 -> -13764525 | E11: =-'Supporting schedule'!E7 -> -14452751 | F11: =-'Supporting schedule'!F7 -> -15175389 | G11: =-'Supporting schedule'!G7 -> -15934158
A13: Cash Flow From Financing
A14: Debt Issued/ Repaid | C14: =0 -> 0 | D14: =0 -> 0 | E14: =0 -> 0 | F14: =0 -> 0 | G14: =0 -> 0
A16: Net Change in Cash | C16: =SUM(C6:C8)+SUM(C11)+SUM(C14) -> 84526355 | D16: =SUM(D6:D8)+SUM(D11)+SUM(D14) -> 1.1769761e+08 | E16: =SUM(E6:E8)+SUM(E11)+SUM(E14) -> 1.2358249e+08 | F16: =SUM(F6:F8)+SUM(F11)+SUM(F14) -> 1.2976162e+08 | G16: =SUM(G6:G8)+SUM(G11)+SUM(G14) -> 1.362497e+08

Sheet Supporting schedule
B4: FY0 | C4: FY1 | D4: FY2 | E4: FY3 | F4: FY4 | G4: FY5
A5: Depreciation | B5: 220960000 | C5: ='Income statement'!C5*Assumptions!C11 -> 15293917 | D5: ='Income statement'!D5*Assumptions!D11 -> 16058613 | E5: ='Income statement'!E5*Assumptions!E11 -> 16861543 | F5: ='Income statement'!F5*Assumptions!F11 -> 17704620 | G5: ='Income statement'!G5*Assumptions!G11 -> 18589851
A7: Cpaex | C7: ='Income statement'!C5*Assumptions!C10 -> 13109072 | D7: ='Income statement'!D5*Assumptions!D10 -> 13764525 | E7: ='Income statement'!E5*Assumptions!E10 -> 14452751 | F7: ='Income statement'!F5*Assumptions!F10 -> 15175389 | G7: ='Income statement'!G5*Assumptions!G10 -> 15934158
A9: Net Working Capital | B9: -23405000 | C9: ='Income statement'!C5*Assumptions!C12 -> 4369690.5 | D9: ='Income statement'!D5*Assumptions!D12 -> 4588175 | E9: ='Income statement'!E5*Assumptions!E12 -> 4817583.8 | F9: ='Income statement'!F5*Assumptions!F12 -> 5058463 | G9: ='Income statement'!G5*Assumptions!G12 -> 5311386.1
A10: Change in NWC | C10: =C9-B9 -> 27774690 | D10: =D9-C9 -> 218484.53 | E10: =E9-D9 -> 229408.75 | F10: =F9-E9 -> 240879.19 | G10: =G9-F9 -> 252923.15

Sheet DCF
B4: FY1 | C4: FY2 | D4: FY3 | E4: FY4 | F4: FY5
A5: EBIT | B5: ='Income statement'!C9 -> 131090715 | C5: ='Income statement'!D9 -> 1.3764525e+08 | D5: ='Income statement'!E9 -> 1.4452751e+08 | E5: ='Income statement'!F9 -> 1.5175389e+08 | F5: ='Income statement'!G9 -> 1.5934158e+08
A6: Taxes | B6: =B5*Assumptions!C9 -> 20974514 | C6: =C5*Assumptions!D9 -> 22023240 | D6: =D5*Assumptions!E9 -> 23124402 | E6: =E5*Assumptions!F9 -> 24280622 | F6: =F5*Assumptions!G9 -> 25494653
A7: NOPAT | B7: =B5-B6 -> 1.101162e+08 | C7: =C5-C6 -> 1.1562201e+08 | D7: =D5-D6 -> 1.2140311e+08 | E7: =E5-E6 -> 1.2747327e+08 | F7: =F5-F6 -> 1.3384693e+08
A8: Depreciation | B8: ='Supporting schedule'!C5 -> 15293917 | C8: ='Supporting schedule'!D5 -> 16058613 | D8: ='Supporting schedule'!E5 -> 16861543 | E8: ='Supporting schedule'!F5 -> 17704620 | F8: ='Supporting schedule'!G5 -> 18589851
A9: Capex | B9: =-'Supporting schedule'!C7 -> -13109072 | C9: =-'Supporting schedule'!D7 -> -13764525 | D9: =-'Supporting schedule'!E7 -> -14452751 | E9: =-'Supporting schedule'!F7 -> -15175389 | F9: =-'Supporting schedule'!G7 -> -15934158
A10: Change in Working Capital | B10: =-'Supporting schedule'!C10 -> -27774690 | C10: =-'Supporting schedule'!D10 -> -218484.53 | D10: =-'Supporting schedule'!E10 -> -229408.75 | E10: =-'Supporting schedule'!F10 -> -240879.19 | F10: =-'Supporting schedule'!G10 -> -252923.15
A12: Free Cash Flow | B12: =B7+B8+B9+B10 -> 84526355 | C12: =C7+C8+C9+C10 -> 1.1769761e+08 | D12: =D7+D8+D9+D10 -> 1.2358249e+08 | E12: =E7+E8+E9+E10 -> 1.2976162e+08 | F12: =F7+F8+F9+F10 -> 1.362497e+08
A14: Discount Factor | B14: =1/(1+Assumptions!C15)^1 -> 0.92592593 | C14: =1/(1+Assumptions!D15)^2 -> 0.85733882 | D14: =1/(1+Assumptions!E15)^3 -> 0.79383224 | E14: =1/(1+Assumptions!F15)^4 -> 0.73502985 | F14: =1/(1+Assumptions!G15)^5 -> 0.6805832
A15: PV of FCF | B15: =B12*B14 -> 78265144 | C15: =C12*C14 -> 1.0090673e+08 | D15: =D12*D14 -> 98103768 | E15: =E12*E14 -> 95378664 | F15: =F12*F14 -> 92729256
A17: Terminal Value | F17: =F12 * (1 + Assumptions!C16) / (Assumptions!C15 - Assumptions!C16) -> 2.539199e+09
A18: PV of Terminal Value | F18: =F17*F14 -> 1.7281361e+09
A20: Enterprise Value | B20: =SUM(B15:F15)+F18 -> 2.1935197e+09
A21: Net Debt | B21: ='Balance sheet '!B12 - 'Balance sheet '!B6 -> 43960000
A22: Equity Value | B22: =B20 - B21 -> 2.1495597e+09
A23: Shares Outstanding | B23: 14773260
A24: Implied Share Price | B24: =B22/B23 -> 145.50341

Sheet Sensitivity
B4: 0.015 | C4: 0.02 | D4: 0.025 | E4: 0.03 | F4: 0.035
A5: 0.07 | B5: {=_xlfn.LET( _xlpm.w, $A5, _xlpm.g, B$4, _xlpm.fcf, DCF!$B$12:$F$12, _xlpm.yrs, {1,2,3,4,5}, _xlpm.df, 1/(1+_xlpm.w)^_xlpm.yrs, _xlpm.pv_fcf, SUM(_xlpm.fcf*_xlpm.df), _xlpm.tv, INDEX(_xlpm.fcf,1,5)*(1+_xlpm.g)/(_xlpm.w-_xlpm.g), _xlpm.pv_tv, _xlpm.tv/(1+_xlpm.w)^5, _xlpm.ev, _xlpm.pv_fcf+_xlpm.pv_tv, _xlpm.netdebt, DCF!$B$21, _xlpm.shares, DCF!$B$23, (_xlpm.ev-_xlpm.netdebt)/_xlpm.shares )} -> 150.7865 | C5: {=_xlfn.LET( _xlpm.w, $A5, _xlpm.g, C$4, _xlpm.fcf, DCF!$B$12:$F$12, _xlpm.yrs, {1,2,3,4,5}, _xlpm.df, 1/(1+_xlpm.w)^_xlpm.yrs, _xlpm.pv_fcf, SUM(_xlpm.fcf*_xlpm.df), _xlpm.tv, INDEX(_xlpm.fcf,1,5)*(1+_xlpm.g)/(_xlpm.w-_xlpm.g), _xlpm.pv_tv, _xlpm.tv/(1+_xlpm.w)^5, _xlpm.ev, _xlpm.pv_fcf+_xlpm.pv_tv, _xlpm.netdebt, DCF!$B$21, _xlpm.shares, DCF!$B$23, (_xlpm.ev-_xlpm.netdebt)/_xlpm.shares )} -> 163.57918 | D5: {=_xlfn.LET( _xlpm.w, $A5, _xlpm.g, D$4, _xlpm.fcf, DCF!$B$12:$F$12, _xlpm.yrs, {1,2,3,4,5}, _xlpm.df, 1/(1+_xlpm.w)^_xlpm.yrs, _xlpm.pv_fcf, SUM(_xlpm.fcf*_xlpm.df), _xlpm.tv, INDEX(_xlpm.fcf,1,5)*(1+_xlpm.g)/(_xlpm.w-_xlpm.g), _xlpm.pv_tv, _xlpm.tv/(1+_xlpm.w)^5, _xlpm.ev, _xlpm.pv_fcf+_xlpm.pv_tv, _xlpm.netdebt, DCF!$B$21, _xlpm.shares, DCF!$B$23, (_xlpm.ev-_xlpm.netdebt)/_xlpm.shares )} -> 179.21467 | E5: {=_xlfn.LET( _xlpm.w, $A5, _xlpm.g, E$4, _xlpm.fcf, DCF!$B$12:$F$12, _xlpm.yrs, {1,2,3,4,5}, _xlpm.df, 1/(1+_xlpm.w)^_xlpm.yrs, _xlpm.pv_fcf, SUM(_xlpm.fcf*_xlpm.df), _xlpm.tv, INDEX(_xlpm.fcf,1,5)*(1+_xlpm.g)/(_xlpm.w-_xlpm.g), _xlpm.pv_tv, _xlpm.tv/(1+_xlpm.w)^5, _xlpm.ev, _xlpm.pv_fcf+_xlpm.pv_tv, _xlpm.netdebt, DCF!$B$21, _xlpm.shares, DCF!$B$23, (_xlpm.ev-_xlpm.netdebt)/_xlpm.shares )} -> 198.75904 | F5: {=_xlfn.LET( _xlpm.w, $A5, _xlpm.g, F$4, _xlpm.fcf, DCF!$B$12:$F$12, _xlpm.yrs, {1,2,3,4,5}, _xlpm.df, 1/(1+_xlpm.w)^_xlpm.yrs, _xlpm.pv_fcf, SUM(_xlpm.fcf*_xlpm.df), _xlpm.tv, INDEX(_xlpm.fcf,1,5)*(1+_xlpm.g)/(_xlpm.w-_xlpm.g), _xlpm.pv_tv, _xlpm.tv/(1+_xlpm.w)^5, _xlpm.ev, _xlpm.pv_fcf+_xlpm.pv_tv, _xlpm.netdebt, DCF!$B$21, _xlpm.shares, DCF!$B$23, (_xlpm.ev-_xlpm.netdebt)/_xlpm.shares )} -> 223.88751
A6: 0.075 | B6: {=_xlfn.LET( _xlpm.w, $A6, _xlpm.g, B$4, _xlpm.fcf, DCF!$B$12:$F$12, _xlpm.yrs, {1,2,3,4,5}, _xlpm.df, 1/(1+_xlpm.w)^_xlpm.yrs, _xlpm.pv_fcf, SUM(_xlpm.fcf*_xlpm.df), _xlpm.tv, INDEX(_xlpm.fcf,1,5)*(1+_xlpm.g)/(_xlpm.w-_xlpm.g), _xlpm.pv_tv, _xlpm.tv/(1+_xlpm.w)^5, _xlpm.ev, _xlpm.pv_fcf+_xlpm.pv_tv, _xlpm.netdebt, DCF!$B$21, _xlpm.shares, DCF!$B$23, (_xlpm.ev-_xlpm.netdebt)/_xlpm.shares )} -> 137.65133 | C6: {=_xlfn.LET( _xlpm.w, $A6, _xlpm.g, C$4, _xlpm.fcf, DCF!$B$12:$F$12, _xlpm.yrs, {1,2,3,4,5}, _xlpm.df, 1/(1+_xlpm.w)^_xlpm.yrs, _xlpm.pv_fcf, SUM(_xlpm.fcf*_xlpm.df), _xlpm.tv, INDEX(_xlpm.fcf,1,5)*(1+_xlpm.g)/(_xlpm.w-_xlpm.g), _xlpm.pv_tv, _xlpm.tv/(1+_xlpm.w)^5, _xlpm.ev, _xlpm.pv_fcf+_xlpm.pv_tv, _xlpm.netdebt, DCF!$B$21, _xlpm.shares, DCF!$B$23, (_xlpm.ev-_xlpm.netdebt)/_xlpm.shares )} -> 148.11493 | D6: {=_xlfn.LET( _xlpm.w, $A6, _xlpm.g, D$4, _xlpm.fcf, DCF!$B$12:$F$12, _xlpm.yrs, {1,2,3,4,5}, _xlpm.df, 1/(1+_xlpm.w)^_xlpm.yrs, _xlpm.pv_fcf, SUM(_xlpm.fcf*_xlpm.df), _xlpm.tv, INDEX(_xlpm.fcf,1,5)*(1+_xlpm.g)/(_xlpm.w-_xlpm.g), _xlpm.pv_tv, _xlpm.tv/(1+_xlpm.w)^5, _xlpm.ev, _xlpm.pv_fcf+_xlpm.pv_tv, _xlpm.netdebt, DCF!$B$21, _xlpm.shares, DCF!$B$23, (_xlpm.ev-_xlpm.netdebt)/_xlpm.shares )} -> 160.67126 | E6: {=_xlfn.LET( _xlpm.w, $A6, _xlpm.g, E$4, _xlpm.fcf, DCF!$B$12:$F$12, _xlpm.yrs, {1,2,3,4,5}, _xlpm.df, 1/(1+_xlpm.w)^_xlpm.yrs, _xlpm.pv_fcf, SUM(_xlpm.fcf*_xlpm.df), _xlpm.tv, INDEX(_xlpm.fcf,1,5)*(1+_xlpm.g)/(_xlpm.w-_xlpm.g), _xlpm.pv_tv, _xlpm.tv/(1+_xlpm.w)^5, _xlpm.ev, _xlpm.pv_fcf+_xlpm.pv_tv, _xlpm.netdebt, DCF!$B$21, _xlpm.shares, DCF!$B$23, (_xlpm.ev-_xlpm.netdebt)/_xlpm.shares )} -> 176.01788 | F6: {=_xlfn.LET( _xlpm.w, $A6, _xlpm.g, F$4, _xlpm.fcf, DCF!$B$12:$F$12, _xlpm.yrs, {1,2,3,4,5}, _xlpm.df, 1/(1+_xlpm.w)^_xlpm.yrs, _xlpm.pv_fcf, SUM(_xlpm.fcf*_xlpm.df), _xlpm.tv, INDEX(_xlpm.fcf,1,5)*(1+_xlpm.g)/(_xlpm.w-_xlpm.g), _xlpm.pv_tv, _xlpm.tv/(1+_xlpm.w)^5, _xlpm.ev, _xlpm.pv_fcf+_xlpm.pv_tv, _xlpm.netdebt, DCF!$B$21, _xlpm.shares, DCF!$B$23, (_xlpm.ev-_xlpm.netdebt)/_xlpm.shares )} -> 195.20116
A7: 0.08 | B7: {=_xlfn.LET( _xlpm.w, $A7, _xlpm.g, B$4, _xlpm.fcf, DCF!$B$12:$F$12, _xlpm.yrs, {1,2,3,4,5}, _xlpm.df, 1/(1+_xlpm.w)^_xlpm.yrs, _xlpm.pv_fcf, SUM(_xlpm.fcf*_xlpm.df), _xlpm.tv, INDEX(_xlpm.fcf,1,5)*(1+_xlpm.g)/(_xlpm.w-_xlpm.g), _xlpm.pv_tv, _xlpm.tv/(1+_xlpm.w)^5, _xlpm.ev, _xlpm.pv_fcf+_xlpm.pv_tv, _xlpm.netdebt, DCF!$B$21, _xlpm.shares, DCF!$B$23, (_xlpm.ev-_xlpm.netdebt)/_xlpm.shares )} -> 126.54124 | C7: {=_xlfn.LET( _xlpm.w, $A7, _xlpm.g, C$4, _xlpm.fcf, DCF!$B$12:$F$12, _xlpm.yrs, {1,2,3,4,5}, _xlpm.df, 1/(1+_xlpm.w)^_xlpm.yrs, _xlpm.pv_fcf, SUM(_xlpm.fcf*_xlpm.df), _xlpm.tv, INDEX(_xlpm.fcf,1,5)*(1+_xlpm.g)/(_xlpm.w-_xlpm.g), _xlpm.pv_tv, _xlpm.tv/(1+_xlpm.w)^5, _xlpm.ev, _xlpm.pv_fcf+_xlpm.pv_tv, _xlpm.netdebt, DCF!$B$21, _xlpm.shares, DCF!$B$23, (_xlpm.ev-_xlpm.netdebt)/_xlpm.shares )} -> 135.23223 | D7: {=_xlfn.LET( _xlpm.w, $A7, _xlpm.g, D$4, _xlpm.fcf, DCF!$B$12:$F$12, _xlpm.yrs, {1,2,3,4,5}, _xlpm.df, 1/(1+_xlpm.w)^_xlpm.yrs, _xlpm.pv_fcf, SUM(_xlpm.fcf*_xlpm.df), _xlpm.tv, INDEX(_xlpm.fcf,1,5)*(1+_xlpm.g)/(_xlpm.w-_xlpm.g), _xlpm.pv_tv, _xlpm.tv/(1+_xlpm.w)^5, _xlpm.ev, _xlpm.pv_fcf+_xlpm.pv_tv, _xlpm.netdebt, DCF!$B$21, _xlpm.shares, DCF!$B$23, (_xlpm.ev-_xlpm.netdebt)/_xlpm.shares )} -> 145.50341 | E7: {=_xlfn.LET( _xlpm.w, $A7, _xlpm.g, E$4, _xlpm.fcf, DCF!$B$12:$F$12, _xlpm.yrs, {1,2,3,4,5}, _xlpm.df, 1/(1+_xlpm.w)^_xlpm.yrs, _xlpm.pv_fcf, SUM(_xlpm.fcf*_xlpm.df), _xlpm.tv, INDEX(_xlpm.fcf,1,5)*(1+_xlpm.g)/(_xlpm.w-_xlpm.g), _xlpm.pv_tv, _xlpm.tv/(1+_xlpm.w)^5, _xlpm.ev, _xlpm.pv_fcf+_xlpm.pv_tv, _xlpm.netdebt, DCF!$B$21, _xlpm.shares, DCF!$B$23, (_xlpm.ev-_xlpm.netdebt)/_xlpm.shares )} -> 157.82882 | F7: {=_xlfn.LET( _xlpm.w, $A7, _xlpm.g, F$4, _xlpm.fcf, DCF!$B$12:$F$12, _xlpm.yrs, {1,2,3,4,5}, _xlpm.df, 1/(1+_xlpm.w)^_xlpm.yrs, _xlpm.pv_fcf, SUM(_xlpm.fcf*_xlpm.df), _xlpm.tv, INDEX(_xlpm.fcf,1,5)*(1+_xlpm.g)/(_xlpm.w-_xlpm.g), _xlpm.pv_tv, _xlpm.tv/(1+_xlpm.w)^5, _xlpm.ev, _xlpm.pv_fcf+_xlpm.pv_tv, _xlpm.netdebt, DCF!$B$21, _xlpm.shares, DCF!$B$23, (_xlpm.ev-_xlpm.netdebt)/_xlpm.shares )} -> 172.89322
A8: 0.085 | B8: {=_xlfn.LET( _xlpm.w, $A8, _xlpm.g, B$4, _xlpm.fcf, DCF!$B$12:$F$12, _xlpm.yrs, {1,2,3,4,5}, _xlpm.df, 1/(1+_xlpm.w)^_xlpm.yrs, _xlpm.pv_fcf, SUM(_xlpm.fcf*_xlpm.df), _xlpm.tv, INDEX(_xlpm.fcf,1,5)*(1+_xlpm.g)/(_xlpm.w-_xlpm.g), _xlpm.pv_tv, _xlpm.tv/(1+_xlpm.w)^5, _xlpm.ev, _xlpm.pv_fcf+_xlpm.pv_tv, _xlpm.netdebt, DCF!$B$21, _xlpm.shares, DCF!$B$23, (_xlpm.ev-_xlpm.netdebt)/_xlpm.shares )} -> 117.0222 | C8: {=_xlfn.LET( _xlpm.w, $A8, _xlpm.g, C$4, _xlpm.fcf, DCF!$B$12:$F$12, _xlpm.yrs, {1,2,3,4,5}, _xlpm.df, 1/(1+_xlpm.w)^_xlpm.yrs, _xlpm.pv_fcf, SUM(_xlpm.fcf*_xlpm.df), _xlpm.tv, INDEX(_xlpm.fcf,1,5)*(1+_xlpm.g)/(_xlpm.w-_xlpm.g), _xlpm.pv_tv, _xlpm.tv/(1+_xlpm.w)^5, _xlpm.ev, _xlpm.pv_fcf+_xlpm.pv_tv, _xlpm.netdebt, DCF!$B$21, _xlpm.shares, DCF!$B$23, (_xlpm.ev-_xlpm.netdebt)/_xlpm.shares )} -> 124.33526 | D8: {=_xlfn.LET( _xlpm.w, $A8, _xlpm.g, D$4, _xlpm.fcf, DCF!$B$12:$F$12, _xlpm.yrs, {1,2,3,4,5}, _xlpm.df, 1/(1+_xlpm.w)^_xlpm.yrs, _xlpm.pv_fcf, SUM(_xlpm.fcf*_xlpm.df), _xlpm.tv, INDEX(_xlpm.fcf,1,5)*(1+_xlpm.g)/(_xlpm.w-_xlpm.g), _xlpm.pv_tv, _xlpm.tv/(1+_xlpm.w)^5, _xlpm.ev, _xlpm.pv_fcf+_xlpm.pv_tv, _xlpm.netdebt, DCF!$B$21, _xlpm.shares, DCF!$B$23, (_xlpm.ev-_xlpm.netdebt)/_xlpm.shares )} -> 132.86716 | E8: {=_xlfn.LET( _xlpm.w, $A8, _xlpm.g, E$4, _xlpm.fcf, DCF!$B$12:$F$12, _xlpm.yrs, {1,2,3,4,5}, _xlpm.df, 1/(1+_xlpm.w)^_xlpm.yrs, _xlpm.pv_fcf, SUM(_xlpm.fcf*_xlpm.df), _xlpm.tv, INDEX(_xlpm.fcf,1,5)*(1+_xlpm.g)/(_xlpm.w-_xlpm.g), _xlpm.pv_tv, _xlpm.tv/(1+_xlpm.w)^5, _xlpm.ev, _xlpm.pv_fcf+_xlpm.pv_tv, _xlpm.netdebt, DCF!$B$21, _xlpm.shares, DCF!$B$23, (_xlpm.ev-_xlpm.netdebt)/_xlpm.shares )} -> 142.95031 | F8: {=_xlfn.LET( _xlpm.w, $A8, _xlpm.g, F$4, _xlpm.fcf, DCF!$B$12:$F$12, _xlpm.yrs, {1,2,3,4,5}, _xlpm.df, 1/(1+_xlpm.w)^_xlpm.yrs, _xlpm.pv_fcf, SUM(_xlpm.fcf*_xlpm.df), _xlpm.tv, INDEX(_xlpm.fcf,1,5)*(1+_xlpm.g)/(_xlpm.w-_xlpm.g), _xlpm.pv_tv, _xlpm.tv/(1+_xlpm.w)^5, _xlpm.ev, _xlpm.pv_fcf+_xlpm.pv_tv, _xlpm.netdebt, DCF!$B$21, _xlpm.shares, DCF!$B$23, (_xlpm.ev-_xlpm.netdebt)/_xlpm.shares )} -> 155.05009
A9: 0.09 | B9: {=_xlfn.LET( _xlpm.w, $A9, _xlpm.g, B$4, _xlpm.fcf, DCF!$B$12:$F$12, _xlpm.yrs, {1,2,3,4,5}, _xlpm.df, 1/(1+_xlpm.w)^_xlpm.yrs, _xlpm.pv_fcf, SUM(_xlpm.fcf*_xlpm.df), _xlpm.tv, INDEX(_xlpm.fcf,1,5)*(1+_xlpm.g)/(_xlpm.w-_xlpm.g), _xlpm.pv_tv, _xlpm.tv/(1+_xlpm.w)^5, _xlpm.ev, _xlpm.pv_fcf+_xlpm.pv_tv, _xlpm.netdebt, DCF!$B$21, _xlpm.shares, DCF!$B$23, (_xlpm.ev-_xlpm.netdebt)/_xlpm.shares )} -> 108.77594 | C9: {=_xlfn.LET( _xlpm.w, $A9, _xlpm.g, C$4, _xlpm.fcf, DCF!$B$12:$F$12, _xlpm.yrs, {1,2,3,4,5}, _xlpm.df, 1/(1+_xlpm.w)^_xlpm.yrs, _xlpm.pv_fcf, SUM(_xlpm.fcf*_xlpm.df), _xlpm.tv, INDEX(_xlpm.fcf,1,5)*(1+_xlpm.g)/(_xlpm.w-_xlpm.g), _xlpm.pv_tv, _xlpm.tv/(1+_xlpm.w)^5, _xlpm.ev, _xlpm.pv_fcf+_xlpm.pv_tv, _xlpm.netdebt, DCF!$B$21, _xlpm.shares, DCF!$B$23, (_xlpm.ev-_xlpm.netdebt)/_xlpm.shares )} -> 114.99843 | D9: {=_xlfn.LET( _xlpm.w, $A9, _xlpm.g, D$4, _xlpm.fcf, DCF!$B$12:$F$12, _xlpm.yrs, {1,2,3,4,5}, _xlpm.df, 1/(1+_xlpm.w)^_xlpm.yrs, _xlpm.pv_fcf, SUM(_xlpm.fcf*_xlpm.df), _xlpm.tv, INDEX(_xlpm.fcf,1,5)*(1+_xlpm.g)/(_xlpm.w-_xlpm.g), _xlpm.pv_tv, _xlpm.tv/(1+_xlpm.w)^5, _xlpm.ev, _xlpm.pv_fcf+_xlpm.pv_tv, _xlpm.netdebt, DCF!$B$21, _xlpm.shares, DCF!$B$23, (_xlpm.ev-_xlpm.netdebt)/_xlpm.shares )} -> 122.17822 | E9: {=_xlfn.LET( _xlpm.w, $A9, _xlpm.g, E$4, _xlpm.fcf, DCF!$B$12:$F$12, _xlpm.yrs, {1,2,3,4,5}, _xlpm.df, 1/(1+_xlpm.w)^_xlpm.yrs, _xlpm.pv_fcf, SUM(_xlpm.fcf*_xlpm.df), _xlpm.tv, INDEX(_xlpm.fcf,1,5)*(1+_xlpm.g)/(_xlpm.w-_xlpm.g), _xlpm.pv_tv, _xlpm.tv/(1+_xlpm.w)^5, _xlpm.ev, _xlpm.pv_fcf+_xlpm.pv_tv, _xlpm.netdebt, DCF!$B$21, _xlpm.shares, DCF!$B$23, (_xlpm.ev-_xlpm.netdebt)/_xlpm.shares )} -> 130.55464 | F9: {=_xlfn.LET( _xlpm.w, $A9, _xlpm.g, F$4, _xlpm.fcf, DCF!$B$12:$F$12, _xlpm.yrs, {1,2,3,4,5}, _xlpm.df, 1/(1+_xlpm.w)^_xlpm.yrs, _xlpm.pv_fcf, SUM(_xlpm.fcf*_xlpm.df), _xlpm.tv, INDEX(_xlpm.fcf,1,5)*(1+_xlpm.g)/(_xlpm.w-_xlpm.g), _xlpm.pv_tv, _xlpm.tv/(1+_xlpm.w)^5, _xlpm.ev, _xlpm.pv_fcf+_xlpm.pv_tv, _xlpm.netdebt, DCF!$B$21, _xlpm.shares, DCF!$B$23, (_xlpm.ev-_xlpm.netdebt)/_xlpm.shares )} -> 140.45405
A13: Impled Share Price
A14: Bull Case | B14: =B6 -> 137.65133
A15: Base Case | B15: =B7 -> 126.54124
A16: Bear Case | B16: =B8 -> 117.0222
